PyFinitDiff/__init__.py
PyFinitDiff/_version.py
PyFinitDiff/boundary_values.py
PyFinitDiff/diagonal.py
PyFinitDiff/directories.py
PyFinitDiff/triplet.py
PyFinitDiff/coefficients/__init__.py
PyFinitDiff/coefficients/backward.py
PyFinitDiff/coefficients/central.py
PyFinitDiff/coefficients/forward.py
PyFinitDiff/finite_difference_1D/__init__.py
PyFinitDiff/finite_difference_1D/boundaries.py
PyFinitDiff/finite_difference_1D/derivative.py
PyFinitDiff/finite_difference_1D/finite_difference.py
PyFinitDiff/finite_difference_1D/utils.py
PyFinitDiff/finite_difference_2D/__init__.py
PyFinitDiff/finite_difference_2D/boundaries.py
PyFinitDiff/finite_difference_2D/derivative.py
PyFinitDiff/finite_difference_2D/finite_difference.py
PyFinitDiff/finite_difference_2D/utils.py
pyfinitdiff-2.3.1.dist-info/licenses/LICENSE
pyfinitdiff-2.3.1.dist-info/METADATA
pyfinitdiff-2.3.1.dist-info/WHEEL
pyfinitdiff-2.3.1.dist-info/top_level.txt
pyfinitdiff-2.3.1.dist-info/RECORD
