Metadata-Version: 2.4
Name: PyFinitDiff
Version: 2.3.1
Summary: A package for generating finite-difference matrices, particularly suited for physics and engineering applications.
Author-email: Martin Poinsinet de Sivry-Houle <martin.poinsinet.de.sivry@gmail.com>
License: MIT License
Project-URL: Homepage, https://github.com/MartinPdeS/PyFinitDiff
Project-URL: Documentation, https://martinpdes.github.io/PyFinitDiff/
Project-URL: Repository, https://github.com/MartinPdeS/PyFinitDiff.git
Keywords: finite-difference,solving,linear algebra,physics,matrix,engineering
Classifier: Programming Language :: Python
Classifier: Programming Language :: Python :: 3
Classifier: Programming Language :: Python :: 3.11
Classifier: Programming Language :: Python :: 3.12
Classifier: Programming Language :: Python :: Implementation :: CPython
Classifier: Development Status :: 4 - Beta
Classifier: Topic :: Scientific/Engineering :: Physics
Classifier: License :: OSI Approved :: MIT License
Classifier: Intended Audience :: Science/Research
Requires-Python: >=3.10
License-File: LICENSE
Requires-Dist: scipy>=1.14
Requires-Dist: pydantic
Requires-Dist: numpy
Requires-Dist: MPSPlots
Requires-Dist: tabulate
Provides-Extra: testing
Requires-Dist: pytest<9.0,>=7.4; extra == "testing"
Requires-Dist: pytest-cov<7,>=2; extra == "testing"
Requires-Dist: pytest-json-report~=1.5; extra == "testing"
Requires-Dist: coverage~=7.6; extra == "testing"
Provides-Extra: documentation
Requires-Dist: numpydoc~=1.8; extra == "documentation"
Requires-Dist: sphinx>=6; extra == "documentation"
Requires-Dist: sphinx-gallery~=0.17; extra == "documentation"
Requires-Dist: sphinx-rtd-theme~=3.0; extra == "documentation"
Requires-Dist: pydata-sphinx-theme~=0.15; extra == "documentation"
Provides-Extra: dev
Requires-Dist: flake8==7.2.0; extra == "dev"
Dynamic: license-file
